LICENSE
file_notes/__init__.py
file_notes/file_notes.py
file_notes/huepy.py
file_notes/main.py
file_notes-0.0.4.dev0.dist-info/entry_points.txt
file_notes-0.0.4.dev0.dist-info/LICENSE
file_notes-0.0.4.dev0.dist-info/WHEEL
file_notes-0.0.4.dev0.dist-info/METADATA
file_notes-0.0.4.dev0.dist-info/RECORD
