Metadata-Version: 2.1
Name: file-notes
Version: 0.0.4.dev0
Summary: file-notes can add note information to the file. It works with Python 3.6+.
Home-page: https://github.com/flyerjia/file-notes
License: MIT
Keywords: file note,script
Author: Flyer-Jia
Author-email: flyerjia@outlook.com
Requires-Python: >=3.6,<4.0
Classifier: License :: OSI Approved :: MIT License
Classifier: Programming Language :: Python :: 3
Classifier: Programming Language :: Python :: 3.10
Classifier: Programming Language :: Python :: 3.6
Classifier: Programming Language :: Python :: 3.7
Classifier: Programming Language :: Python :: 3.8
Classifier: Programming Language :: Python :: 3.9
Project-URL: Repository, https://github.com/flyerjia/file-notes
